unicorn_bybit_websocket_api/__init__.c
unicorn_bybit_websocket_api/__init__.cp310-win32.pyd
unicorn_bybit_websocket_api/__init__.py
unicorn_bybit_websocket_api/__init__.pyi
unicorn_bybit_websocket_api/connection.c
unicorn_bybit_websocket_api/connection.cp310-win32.pyd
unicorn_bybit_websocket_api/connection.py
unicorn_bybit_websocket_api/connection.pyi
unicorn_bybit_websocket_api/connection_settings.c
unicorn_bybit_websocket_api/connection_settings.cp310-win32.pyd
unicorn_bybit_websocket_api/connection_settings.py
unicorn_bybit_websocket_api/connection_settings.pyi
unicorn_bybit_websocket_api/exceptions.c
unicorn_bybit_websocket_api/exceptions.cp310-win32.pyd
unicorn_bybit_websocket_api/exceptions.py
unicorn_bybit_websocket_api/exceptions.pyi
unicorn_bybit_websocket_api/licensing_exceptions.c
unicorn_bybit_websocket_api/licensing_exceptions.cp310-win32.pyd
unicorn_bybit_websocket_api/licensing_exceptions.py
unicorn_bybit_websocket_api/licensing_exceptions.pyi
unicorn_bybit_websocket_api/licensing_manager.c
unicorn_bybit_websocket_api/licensing_manager.cp310-win32.pyd
unicorn_bybit_websocket_api/licensing_manager.py
unicorn_bybit_websocket_api/licensing_manager.pyi
unicorn_bybit_websocket_api/manager.c
unicorn_bybit_websocket_api/manager.cp310-win32.pyd
unicorn_bybit_websocket_api/manager.py
unicorn_bybit_websocket_api/manager.pyi
unicorn_bybit_websocket_api/restclient.c
unicorn_bybit_websocket_api/restclient.cp310-win32.pyd
unicorn_bybit_websocket_api/restclient.py
unicorn_bybit_websocket_api/restclient.pyi
unicorn_bybit_websocket_api/sockets.c
unicorn_bybit_websocket_api/sockets.cp310-win32.pyd
unicorn_bybit_websocket_api/sockets.py
unicorn_bybit_websocket_api/sockets.pyi
unicorn_bybit_websocket_api-0.1.0.dist-info/LICENSE
unicorn_bybit_websocket_api-0.1.0.dist-info/METADATA
unicorn_bybit_websocket_api-0.1.0.dist-info/WHEEL
unicorn_bybit_websocket_api-0.1.0.dist-info/top_level.txt
unicorn_bybit_websocket_api-0.1.0.dist-info/RECORD
