Metadata-Version: 2.1
Name: unicorn-bybit-websocket-api
Version: 0.1.0
Summary: A Python SDK by LUCIT to use the Bybit Websocket API`s in a simple, fast, flexible, robust and fully-featured way.
Home-page: https://github.com/LUCIT-Systems-and-Development/unicorn-bybit-websocket-api
Author: LUCIT Systems and Development
Author-email: info@lucit.tech
License: LSOSL - LUCIT Synergetic Open Source License
Project-URL: Howto, https://www.lucit.tech/unicorn-bybit-websocket-api.html#howto
Project-URL: Documentation, https://unicorn-bybit-websocket-api.docs.lucit.tech
Project-URL: Wiki, https://github.com/LUCIT-Systems-and-Development/unicorn-bybit-websocket-api/wiki
Project-URL: Author, https://www.lucit.tech
Project-URL: Changes, https://unicorn-bybit-websocket-api.docs.lucit.tech/changelog.html
Project-URL: License, https://unicorn-bybit-websocket-api.docs.lucit.tech/license.html
Project-URL: Issue Tracker, https://github.com/LUCIT-Systems-and-Development/unicorn-bybit-websocket-api/issues
Project-URL: Chat, https://gitter.im/unicorn-trading-suite/unicorn-bybit-websocket-api
Project-URL: Telegram, https://t.me/unicorndevs
Project-URL: Get Support, https://www.lucit.tech/get-support.html
Project-URL: LUCIT Online Shop, https://shop.lucit.services/software
Keywords: bybit,asyncio,async,asynchronous,concurrent,websocket-api,webstream-api,bybit-websocket,bybit-webstream,webstream,websocket,api
Classifier: Development Status :: 4 - Beta
Classifier: Programming Language :: Python :: 3.7
Classifier: Programming Language :: Python :: 3.8
Classifier: Programming Language :: Python :: 3.9
Classifier: Programming Language :: Python :: 3.10
Classifier: Programming Language :: Python :: 3.11
Classifier: Programming Language :: Python :: 3.12
Classifier: Programming Language :: Cython
Classifier: License :: Other/Proprietary License
Classifier: Intended Audience :: Developers
Classifier: Intended Audience :: Financial and Insurance Industry
Classifier: Intended Audience :: Information Technology
Classifier: Intended Audience :: Science/Research
Classifier: Operating System :: OS Independent
Classifier: Topic :: Office/Business :: Financial :: Investment
Classifier: Topic :: Software Development :: Libraries :: Python Modules
Classifier: Framework :: AsyncIO
Requires-Python: >=3.7.0
License-File: LICENSE
Requires-Dist: colorama
Requires-Dist: requests >=2.31.0
Requires-Dist: websocket-client
Requires-Dist: websockets ==11.0.3
Requires-Dist: flask-restful
Requires-Dist: cheroot
Requires-Dist: flask
Requires-Dist: lucit-licensing-python >=1.8.2
Requires-Dist: ujson
Requires-Dist: psutil
Requires-Dist: PySocks
Requires-Dist: typing-extensions
Requires-Dist: Cython
